APB/slave2.v
////////////////////////////////////////////////
//
// Name:   Shubhi Agrawal
// Design: APB2 Protocol Slave-2
// Date:   13-06-2021
//
///////////////////////////////////////////////






`timescale 1ns/1ns



module slave2(
         input PCLK,PRESETn,
         input PSEL,PENABLE,PWRITE,
         input [7:0]PADDR,PWDATA,
        output [7:0]PRDATA2,
        output reg PREADY );
    
     reg [7:0]reg_addr;

     reg [7:0] mem2 [0:63];

    assign PRDATA2 =  mem2[reg_addr];



    always @(*)
       begin
         if(!PRESETn)
              PREADY = 0;
          else
	  if(PSEL && !PENABLE && !PWRITE)
	     begin PREADY = 0; end
	         
	  else if(PSEL && PENABLE && !PWRITE)
	     begin  PREADY = 1;
                    reg_addr =  PADDR; 
	       end
          else if(PSEL && !PENABLE && PWRITE)
	     begin  PREADY = 0; end

	  else if(PSEL && PENABLE && PWRITE)
	     begin  PREADY = 1;
	            mem2[PADDR] = PWDATA; end

           else PREADY = 0;
        end
    endmodule
 /*  reg [7:0]mem[0:63];
  
 integer i;
 
  initial
    begin
     for(i=0;i<64;i=i+1)
     begin  mem[i] = {$random};
             #1;
     end
   end
       // repeat(100)
       // begin #50 mem[$random] = {$random}; end
  
*/
   // assign PRDATA2 = (PSEL && PENABLE && PWRITE) ? mem[reg_addr] : 8'dz;
   // ram dhy(PRDATA2,PWDATA,P,PWRITE,PREADY);
/*
module ram(data_out, data_in,addr,PWRITE,PREADY);
 
 parameter ddr_size = 8, word_size = 8, memory_size = 64;

 input [7:0]addr;
 input PWRITE,PREADY;
 input [7:0] data_in;
 output [7:0]data_out;

reg [7:0] mem [0:63];

assign data_out = PREADY ? mem[addr] : 8'bz;

always @(PWRITE,PREADY)
 if(PWRITE) mem[addr] = data_in;

endmodule*/
/*
module RAM_test;

 reg [7:0]address;
 wire [7:0] data_out;
 reg [7:0] data_in;
 reg write,select;
integer k,myseed;
ram rgd(data_out, data_in,address,write,select);

 initial
   begin
     for(k=0; k<= 63; k=k+1)
         begin
           data_in = (k + k)%256;
            write =1; select=1;
           #2 write=0; select=0;
        end
initial myseed = 35;

endmodule */
/*    always @(PWRITE,PREADY)
          if(PWRITE & PREADY) mem[PADDR] = PWDATA;

  always @(posedge PCLK)
  begin
	  if(!PRESETn)
		  state <= IDLE;
	  else
               state <= next_state;
       end

       always @(posedge PCLK)
       begin
	       case(state)
		       IDLE: begin
			       if(PSEL & PWRITE)
			       begin PREADY =0;
			       next_state = s_WRITE; end

                               else if(PSEL & !PWRITE)
			       begin PREADY=0;
			       next_state = s_READ; end
                               else
				begin PREADY =0;
	                              next_state = IDLE;  end			       
		              end
		       
		    s_WRITE: begin
			       if(PSEL & PWRITE & PENABLE)
			       begin   PREADY = 1;
			               mem[PADDR] = PWDATA;
				       next_state = IDLE; end
			       else next_state = IDLE ;
		             end

		    s_READ: begin
			       if(PSEL & !PWRITE & PENABLE)
			       begin   PREADY = 1;
			               reg_addr = PADDR;
				       next_state = IDLE; end
			       else next_state = IDLE;
			    end
		    default: begin PREADY=0; 
		                   next_state=IDLE; end
	          endcase
	end


	endmodule
*/

APB/slave1.v

////////////////////////////////////////////////
//
// Name:   Shubhi Agrawal
// Design: APB2 Protocol Slave-1
// Date:   13-06-2021
//
///////////////////////////////////////////////


//`timescale 1ns/1ns



module slave1(
         input PCLK,PRESETn,
         input PSEL,PENABLE,PWRITE,
         input [7:0]PADDR,PWDATA,
        output [7:0]PRDATA1,
        output reg PREADY );
    
     reg [7:0]reg_addr;
     reg [7:0] mem [0:63];

    assign PRDATA1 =  mem[reg_addr];

    always @(*)
       begin
         if(!PRESETn)
              PREADY = 0;
          else
	  if(PSEL && !PENABLE && !PWRITE)
	     begin PREADY = 0; end
	         
	  else if(PSEL && PENABLE && !PWRITE)
	     begin  PREADY = 1;
                    reg_addr =  PADDR; 
	       end
          else if(PSEL && !PENABLE && PWRITE)
	     begin  PREADY = 0; end

	  else if(PSEL && PENABLE && PWRITE)
	     begin  PREADY = 1;
	            mem[PADDR] = PWDATA; end

           else PREADY = 0;
        end
    endmodule

APB/master.v

////////////////////////////////////////////////
//
// Name:   Shubhi Agrawal
// Design: APB2 Protocol Master
// Date:   13-06-2021
//
///////////////////////////////////////////////



//`timescale 1ns/1ns

  module master_bridge(
	input [8:0]apb_write_paddr,apb_read_paddr,
	input [7:0] apb_write_data,PRDATA,         
	input PRESETn,PCLK,READ_WRITE,transfer,PREADY,
	output PSEL1,PSEL2,
	output reg PENABLE,
	output reg [8:0]PADDR,
	output reg PWRITE,
	output reg [7:0]PWDATA,apb_read_data_out,
	output PSLVERR ); 
       // integer i,count;
   
  reg [2:0] state, next_state;

  reg invalid_setup_error,
      setup_error,
      invalid_read_paddr,
      invalid_write_paddr,
      invalid_write_data ;
  
  localparam IDLE = 3'b001, SETUP = 3'b010, ENABLE = 3'b100 ;


  always @(posedge PCLK)
  begin
	if(!PRESETn)
		state <= IDLE;
	else
		state <= next_state; 
  end

  always @(state,transfer,PREADY)

  begin
	if(!PRESETn)
	  next_state = IDLE;
	else
          begin
             PWRITE = ~READ_WRITE;
	     case(state)
                  
		     IDLE: begin 
		              PENABLE =0;

		            if(!transfer)
	        	      next_state = IDLE ;
	                    else
			      next_state = SETUP;
	                   end

	       	SETUP:   begin
			    PENABLE =0;

			    if(READ_WRITE) 
				 //     @(posedge PCLK)
	                       begin   PADDR = apb_read_paddr; end
			    else 
			      begin   
			          //@(posedge PCLK)
                                  PADDR = apb_write_paddr;
				  PWDATA = apb_write_data;  end
			    
			    if(transfer && !PSLVERR)
			      next_state = ENABLE;
		            else
           	              next_state = IDLE;
		           end

	       	ENABLE: 
		     begin if(PSEL1 || PSEL2)
		           PENABLE =1;
			   if(transfer & !PSLVERR)
			   begin
				   if(PREADY)
				   begin
					if(!READ_WRITE)
				         begin
				          
					   next_state = SETUP; end
					else 
					   begin
					   next_state = SETUP; 
				          	   
                                           apb_read_data_out = PRDATA; 
					   end
			            end
				    else next_state = ENABLE;
		              end
		             else next_state = IDLE;
			 end
			   
		        /* if(transfer && !PREADY && READ_WRITE)
                             begin
                              //   repeat(3) @(posedge PCLK)  
                		// begin
			          //  if(!transfer)
                                    //  next_state = IDLE;
		                    //else 
                                      // begin
                                        //if(PREADY) begin
                                          //  next_state = SETUP;
                                            //apb_read_data_out = PRDATA; end
                                        //else
                                            next_state = ENABLE;
				       //end 
                                end
		            end

                       else if(transfer && PREADY && READ_WRITE )
                                 begin
			           apb_read_data_out = PRDATA; 
                                   next_state = SETUP; 
			         end
                                                    
		       else if(transfer && !PREADY && !READ_WRITE)
                                   begin
                                   //   repeat(3) @(posedge PCLK)                                          
			             //   begin
			               // if(!transfer)
                                    //     next_state = IDLE;
				      //  else begin
				        //  if(PREADY) 
					  //   next_state = SETUP;
				          //else
						  next_state = ENABLE;
				         end
			             end 
			     end  
					   
                       else if(transfer && PREADY && !READ_WRITE )
			     begin
                                   next_state = SETUP; 
                                  $strobe($time," Enable write operation"); end   */
                             
                       
                                 default: next_state = IDLE; 
               	endcase
             end
          end


 /*     always @(posedge PCLK) 

      begin
	       PWRITE = ~READ_WRITE;

	      case(state)
		      IDLE: begin
			     
			      PENABLE = 0;
		             end

		      SETUP: begin
			      PENABLE =0;
			      if(READ_WRITE) 
				//  @(posedge PCLK)
			          PADDR = apb_read_paddr;
			      else 
			         //@(posedge PCLK)
                                  PADDR = apb_write_paddr;
				  PWDATA = apb_write_data;
			     end

		      ENABLE: begin
			      PENABLE =1;
		             end
	      endcase
      end */
     assign {PSEL1,PSEL2} = ((state != IDLE) ? (PADDR[8] ? {1'b0,1'b1} : {1'b1,1'b0}) : 2'd0);

  // PSLVERR LOGIC
  
  always @(*)
       begin
        if(!PRESETn)
	    begin 
	     setup_error =0;
	     invalid_read_paddr = 0;
	     invalid_write_paddr = 0;
	     invalid_write_paddr =0 ;
	    end
        else
	 begin	
          begin
	  if(state == IDLE && next_state == ENABLE)
   		  setup_error = 1;
	  else setup_error = 0;
          end
          begin
          if((apb_write_data===8'dx) && (!READ_WRITE) && (state==SETUP || state==ENABLE))
		  invalid_write_data =1;
	  else invalid_write_data = 0;
          end
          begin
	  if((apb_read_paddr===9'dx) && READ_WRITE && (state==SETUP || state==ENABLE))
		  invalid_read_paddr = 1;
	  else  invalid_read_paddr = 0;
          end
          begin
          if((apb_write_paddr===9'dx) && (!READ_WRITE) && (state==SETUP || state==ENABLE))
		  invalid_write_paddr =1;
          else invalid_write_paddr =0;
          end
          begin
	  if(state == SETUP)
            begin
                 if(PWRITE)
                      begin
                         if(PADDR==apb_write_paddr && PWDATA==apb_write_data)
                              setup_error=1'b0;
                         else
                               setup_error=1'b1;
                       end
                 else 
                       begin
                          if (PADDR==apb_read_paddr)
                                 setup_error=1'b0;
                          else
                                 setup_error=1'b1;
                       end    
              end 
          
         else setup_error=1'b0;
         end 
       end
       invalid_setup_error = setup_error ||  invalid_read_paddr || invalid_write_data || invalid_write_paddr  ;
     end 

   assign PSLVERR =  invalid_setup_error ;

	 

 endmodule

APB/apb_protocol.v


`include "master.v"
`include "slave1.v"
`include "slave2.v"



`timescale 1ns/1ns



module APB_Protocol(
                 input PCLK,PRESETn,transfer,READ_WRITE,
                 input [8:0] apb_write_paddr,
		 input [7:0]apb_write_data,
		 input [8:0] apb_read_paddr,
		 output PSLVERR, 
                 output [7:0] apb_read_data_out
          );

       wire [7:0]PWDATA,PRDATA,PRDATA1,PRDATA2;
       wire [8:0]PADDR;

       wire PREADY,PREADY1,PREADY2,PENABLE,PSEL1,PSEL2,PWRITE;
    
      
     //  assign PREADY = READ_WRITE ? (apb_read_paddr[8] ? PREADY2 : PREADY1) : (apb_write_paddr[8] ? PREADY2 : PREADY1);
        assign PREADY = PADDR[8] ? PREADY2 : PREADY1 ;
        assign PRDATA = READ_WRITE ? (PADDR[8] ? PRDATA2 : PRDATA1) : 8'dx ;
       // assign PRDATA = READ_WRITE ? (apb_read_paddr[8] ? PRDATA2 : PRDATA1) : 16'dx;

       master_bridge dut_mas(
	             apb_write_paddr,
		     apb_read_paddr,
		     apb_write_data,
		     PRDATA,         
	             PRESETn,
		     PCLK,
		     READ_WRITE,
		     transfer,
		     PREADY,
	             PSEL1,
		     PSEL2,
		     PENABLE,
	             PADDR,
	             PWRITE,
	             PWDATA,
		     apb_read_data_out,
		     PSLVERR
	               ); 


      slave1 dut1(  PCLK,PRESETn, PSEL1,PENABLE,PWRITE, PADDR[7:0],PWDATA, PRDATA1, PREADY1 );

      slave2 dut2(  PCLK,PRESETn, PSEL2,PENABLE,PWRITE, PADDR[7:0],PWDATA, PRDATA2, PREADY2 );
      


endmodule

APB/test.v



//`timescale 1ns/1ns

//`include "check.mem"

  module test();
 
  reg PCLK,PRESETn,transfer,READ_WRITE;
  reg [8:0]apb_write_paddr;
  reg [7:0]apb_write_data;
  reg [8:0]apb_read_paddr;
  wire [7:0]apb_read_data_out;
  wire PSLVERR;
  reg [7:0]data,expected;

  reg [7:0]mem[0:15];
  
  APB_Protocol dut_c(  PCLK,
	               PRESETn,
		       transfer,
		       READ_WRITE,
                       apb_write_paddr,
		       apb_write_data,
		       apb_read_paddr,
		       PSLVERR, 
                       apb_read_data_out
	                 );
  integer i,j;
  initial
   begin
    PCLK <= 0;
    forever #5 PCLK = ~PCLK;
   end

   initial $readmemh("check.mem",mem); 
    initial
    begin
                         PRESETn<=0; transfer<=0; READ_WRITE =0;
               @(posedge PCLK)      PRESETn = 1;                                     //no write address available but request for write operation
               @(posedge PCLK)      transfer = 1;
     repeat(2) @(posedge PCLK);
               @(negedge PCLK)      Write_slave1;        // write operation

     repeat(3) @(posedge PCLK);    Write_slave2;                                 
               @(posedge PCLK);    apb_write_paddr = 9'd26;  apb_write_data = 9'd9;
     repeat(2) @(posedge PCLK);    apb_write_paddr = 9'd22; apb_write_data = 9'd35;
     repeat(2) @(posedge PCLK);
               @(posedge PCLK)     READ_WRITE =1; PRESETn<=0; transfer<=0; 
               @(posedge PCLK)     PRESETn = 1;
     repeat(3) @(posedge PCLK)     transfer = 1;                             // no read address available but request for read operation
     repeat(2) @(posedge PCLK)     Read_slave1;                             //read operation

     repeat(3) @(posedge PCLK);   Read_slave2;
     repeat(3) @(posedge PCLK);   apb_read_paddr = 9'd45;                 //data not inserted in write operation but requested for read operation
     repeat(4) @(posedge PCLK);
     $finish;
  end

    task Write_slave1;
	 //    reg [7:0]mem [0:15];

     begin
 	transfer =1;
	for (i = 0; i < 8; i=i+1) begin
	repeat(2)@(negedge PCLK)
        begin    
             	data = i;
		apb_write_data = 2*i;
		apb_write_paddr =  {1'b0,data};
	//	mem[i] = (2*i);
                
	 end 
	end
    //	 $writememh("check.mem", mem);

     end
endtask

  task Write_slave2;
     //	   reg [7:0]mem [0:15];

     begin
 	
	for (i = 0; i < 8; i=i+1) begin
	repeat(2)@(negedge PCLK)
        begin  
	        data = i;
		apb_write_paddr = {1'b1,data};
		apb_write_data = i;
	//	mem[i] = i;
		

	 end 
	end
   //	 $writememh("check.mem", mem);
     end
endtask


		 
  task Read_slave1;
     //	  reg [7:0]expected_data;
     //	   reg [7:0]mem [0:15];

      begin 
	for (j = 0;  j< 8; j= j+1)
        begin
	repeat(2)@(negedge PCLK)
          begin  
	  data = j; 
	  apb_read_paddr = {1'b0,data};
      //	  expected_data = mem[j];
         end
        end
      end
  endtask


 task Read_slave2;
      //	 reg [7:0]expected_data;
      //	 reg [7:0]mem [0:15];
      begin 
	for (j = 0;  j< 8; j= j+1)
        begin
	repeat(2)@(negedge PCLK)
          begin
	   data = j;	  
	  apb_read_paddr = {1'b1,data};
      //	  expected_data = mem[j];
      //	  $display("%d",expected_data);
         end
        end
      end
  endtask


  initial
   begin
    $dumpfile("apbWaveform.vcd");
    $dumpvars;
   end

 endmodule

APB/apbWaveform.vcd
$date
	Tue Jun 04 17:12:20 2024
$end
$version
	Icarus Verilog
$end
$timescale
	1ns
$end
$scope module test $end
$var wire 8 ! apb_read_data_out [7:0] $end
$var wire 1 " PSLVERR $end
$var reg 1 # PCLK $end
$var reg 1 $ PRESETn $end
$var reg 1 % READ_WRITE $end
$var reg 9 & apb_read_paddr [8:0] $end
$var reg 8 ' apb_write_data [7:0] $end
$var reg 9 ( apb_write_paddr [8:0] $end
$var reg 8 ) data [7:0] $end
$var reg 1 * transfer $end
$var integer 32 + i [31:0] $end
$var integer 32 , j [31:0] $end
$scope module dut_c $end
$var wire 1 # PCLK $end
$var wire 1 $ PRESETn $end
$var wire 1 % READ_WRITE $end
$var wire 9 - apb_read_paddr [8:0] $end
$var wire 8 . apb_write_data [7:0] $end
$var wire 9 / apb_write_paddr [8:0] $end
$var wire 1 * transfer $end
$var wire 8 0 apb_read_data_out [7:0] $end
$var wire 1 1 PWRITE $end
$var wire 8 2 PWDATA [7:0] $end
$var wire 1 " PSLVERR $end
$var wire 1 3 PSEL2 $end
$var wire 1 4 PSEL1 $end
$var wire 1 5 PREADY2 $end
$var wire 1 6 PREADY1 $end
$var wire 1 7 PREADY $end
$var wire 8 8 PRDATA2 [7:0] $end
$var wire 8 9 PRDATA1 [7:0] $end
$var wire 8 : PRDATA [7:0] $end
$var wire 1 ; PENABLE $end
$var wire 9 < PADDR [8:0] $end
$scope module dut1 $end
$var wire 8 = PADDR [7:0] $end
$var wire 1 # PCLK $end
$var wire 8 > PRDATA1 [7:0] $end
$var wire 1 $ PRESETn $end
$var wire 1 1 PWRITE $end
$var wire 8 ? PWDATA [7:0] $end
$var wire 1 4 PSEL $end
$var wire 1 ; PENABLE $end
$var reg 1 6 PREADY $end
$var reg 8 @ reg_addr [7:0] $end
$upscope $end
$scope module dut2 $end
$var wire 8 A PADDR [7:0] $end
$var wire 1 # PCLK $end
$var wire 8 B PRDATA2 [7:0] $end
$var wire 1 $ PRESETn $end
$var wire 1 1 PWRITE $end
$var wire 8 C PWDATA [7:0] $end
$var wire 1 3 PSEL $end
$var wire 1 ; PENABLE $end
$var reg 1 5 PREADY $end
$var reg 8 D reg_addr [7:0] $end
$upscope $end
$scope module dut_mas $end
$var wire 1 # PCLK $end
$var wire 8 E PRDATA [7:0] $end
$var wire 1 7 PREADY $end
$var wire 1 $ PRESETn $end
$var wire 1 " PSLVERR $end
$var wire 1 % READ_WRITE $end
$var wire 9 F apb_read_paddr [8:0] $end
$var wire 8 G apb_write_data [7:0] $end
$var wire 9 H apb_write_paddr [8:0] $end
$var wire 1 * transfer $end
$var wire 1 3 PSEL2 $end
$var wire 1 4 PSEL1 $end
$var parameter 3 I ENABLE $end
$var parameter 3 J IDLE $end
$var parameter 3 K SETUP $end
$var reg 9 L PADDR [8:0] $end
$var reg 1 ; PENABLE $end
$var reg 8 M PWDATA [7:0] $end
$var reg 1 1 PWRITE $end
$var reg 8 N apb_read_data_out [7:0] $end
$var reg 1 O invalid_read_paddr $end
$var reg 1 P invalid_setup_error $end
$var reg 1 Q invalid_write_data $end
$var reg 1 R invalid_write_paddr $end
$var reg 3 S next_state [2:0] $end
$var reg 1 T setup_error $end
$var reg 3 U state [2:0] $end
$upscope $end
$upscope $end
$scope task Read_slave1 $end
$upscope $end
$scope task Read_slave2 $end
$upscope $end
$scope task Write_slave1 $end
$upscope $end
$scope task Write_slave2 $end
$upscope $end
$upscope $end
$enddefinitions $end
$comment Show the parameter values. $end
$dumpall
b10 K
b1 J
b100 I
$end
#0
$dumpvars
bx U
0T
b1 S
0R
0Q
0P
0O
bx N
bx M
bx L
bx H
bx G
bx F
bx E
bx D
bx C
bx B
bx A
bx @
bx ?
bx >
bx =
bx <
x;
bx :
bx 9
bx 8
07
06
05
x4
x3
bx 2
11
bx 0
bx /
bx .
bx -
bx ,
bx +
0*
bx )
bx (
bx '
bx &
0%
0$
0#
0"
bx !
$end
#5000000000
03
04
0;
b1 U
1$
1#
#10000000000
0#
#15000000000
b10 S
1*
1#
#20000000000
0#
#25000000000
x3
x4
1"
1P
1T
1R
1Q
b100 S
b10 U
1#
#30000000000
0#
#35000000000
0T
b1 S
b100 U
1#
#40000000000
b0 +
0#
#45000000000
03
04
0"
0P
0R
0Q
b10 S
b1 U
1#
#50000000000
b0 (
b0 /
b0 H
b0 '
b0 .
b0 G
b0 )
0#
#55000000000
b0 A
b0 =
03
14
b100 S
b0 2
b0 ?
b0 C
b0 M
b0 <
b0 L
b10 U
1#
#60000000000
b1 +
0#
#65000000000
b10 S
17
16
1;
b100 U
1#
#70000000000
b1 (
b1 /
b1 H
b10 '
b10 .
b10 G
b1 )
0#
#75000000000
07
b1 A
b1 =
06
b100 S
b10 2
b10 ?
b10 C
b10 M
b1 <
b1 L
0;
b10 U
1#
#80000000000
b10 +
0#
#85000000000
b10 S
17
16
1;
b100 U
1#
#90000000000
b10 (
b10 /
b10 H
b100 '
b100 .
b100 G
b10 )
0#
#95000000000
07
b10 A
b10 =
06
b100 S
b100 2
b100 ?
b100 C
b100 M
b10 <
b10 L
0;
b10 U
1#
#100000000000
b11 +
0#
#105000000000
b10 S
17
16
1;
b100 U
1#
#110000000000
b11 (
b11 /
b11 H
b110 '
b110 .
b110 G
b11 )
0#
#115000000000
07
b11 A
b11 =
06
b100 S
b110 2
b110 ?
b110 C
b110 M
b11 <
b11 L
0;
b10 U
1#
#120000000000
b100 +
0#
#125000000000
b10 S
17
16
1;
b100 U
1#
#130000000000
b100 (
b100 /
b100 H
b1000 '
b1000 .
b1000 G
b100 )
0#
#135000000000
07
b100 A
b100 =
06
b100 S
b1000 2
b1000 ?
b1000 C
b1000 M
b100 <
b100 L
0;
b10 U
1#
#140000000000
b101 +
0#
#145000000000
b10 S
17
16
1;
b100 U
1#
#150000000000
b101 (
b101 /
b101 H
b1010 '
b1010 .
b1010 G
b101 )
0#
#155000000000
07
b101 A
b101 =
06
b100 S
b1010 2
b1010 ?
b1010 C
b1010 M
b101 <
b101 L
0;
b10 U
1#
#160000000000
b110 +
0#
#165000000000
b10 S
17
16
1;
b100 U
1#
#170000000000
b110 (
b110 /
b110 H
b1100 '
b1100 .
b1100 G
b110 )
0#
#175000000000
07
b110 A
b110 =
06
b100 S
b1100 2
b1100 ?
b1100 C
b1100 M
b110 <
b110 L
0;
b10 U
1#
#180000000000
b111 +
0#
#185000000000
b10 S
17
16
1;
b100 U
1#
#190000000000
b111 (
b111 /
b111 H
b1110 '
b1110 .
b1110 G
b111 )
0#
#195000000000
07
b111 A
b111 =
06
b100 S
b1110 2
b1110 ?
b1110 C
b1110 M
b111 <
b111 L
0;
b10 U
1#
#200000000000
b1000 +
0#
#205000000000
b10 S
17
16
1;
b100 U
1#
#210000000000
0#
#215000000000
07
06
b100 S
0;
b10 U
1#
#220000000000
0#
#225000000000
b10 S
17
16
1;
b100 U
b0 +
1#
#230000000000
b0 '
b0 .
b0 G
b100000000 (
b100000000 /
b100000000 H
b0 )
0#
#235000000000
13
04
07
b0 A
b0 =
06
b100 S
b0 2
b0 ?
b0 C
b0 M
b100000000 <
b100000000 L
0;
b10 U
1#
#240000000000
b1 +
0#
#245000000000
b10 S
17
15
1;
b100 U
1#
#250000000000
b1 '
b1 .
b1 G
b100000001 (
b100000001 /
b100000001 H
b1 )
0#
#255000000000
07
b1 A
b1 =
05
b100 S
b1 2
b1 ?
b1 C
b1 M
b100000001 <
b100000001 L
0;
b10 U
1#
#260000000000
b10 +
0#
#265000000000
b10 S
17
15
1;
b100 U
1#
#270000000000
b10 '
b10 .
b10 G
b100000010 (
b100000010 /
b100000010 H
b10 )
0#
#275000000000
07
b10 A
b10 =
05
b100 S
b10 2
b10 ?
b10 C
b10 M
b100000010 <
b100000010 L
0;
b10 U
1#
#280000000000
b11 +
0#
#285000000000
b10 S
17
15
1;
b100 U
1#
#290000000000
b11 '
b11 .
b11 G
b100000011 (
b100000011 /
b100000011 H
b11 )
0#
#295000000000
07
b11 A
b11 =
05
b100 S
b11 2
b11 ?
b11 C
b11 M
b100000011 <
b100000011 L
0;
b10 U
1#
#300000000000
b100 +
0#
#305000000000
b10 S
17
15
1;
b100 U
1#
#310000000000
b100 '
b100 .
b100 G
b100000100 (
b100000100 /
b100000100 H
b100 )
0#
#315000000000
07
b100 A
b100 =
05
b100 S
b100 2
b100 ?
b100 C
b100 M
b100000100 <
b100000100 L
0;
b10 U
1#
#320000000000
b101 +
0#
#325000000000
b10 S
17
15
1;
b100 U
1#
#330000000000
b101 '
b101 .
b101 G
b100000101 (
b100000101 /
b100000101 H
b101 )
0#
#335000000000
07
b101 A
b101 =
05
b100 S
b101 2
b101 ?
b101 C
b101 M
b100000101 <
b100000101 L
0;
b10 U
1#
#340000000000
b110 +
0#
#345000000000
b10 S
17
15
1;
b100 U
1#
#350000000000
b110 '
b110 .
b110 G
b100000110 (
b100000110 /
b100000110 H
b110 )
0#
#355000000000
07
b110 A
b110 =
05
b100 S
b110 2
b110 ?
b110 C
b110 M
b100000110 <
b100000110 L
0;
b10 U
1#
#360000000000
b111 +
0#
#365000000000
b10 S
17
15
1;
b100 U
1#
#370000000000
b111 '
b111 .
b111 G
b100000111 (
b100000111 /
b100000111 H
b111 )
0#
#375000000000
07
b111 A
b111 =
05
b100 S
b111 2
b111 ?
b111 C
b111 M
b100000111 <
b100000111 L
0;
b10 U
1#
#380000000000
b1000 +
0#
#385000000000
17
15
b10 S
1;
b100 U
0"
0P
0T
b1001 '
b1001 .
b1001 G
b11010 (
b11010 /
b11010 H
1#
#390000000000
0#
#395000000000
03
14
07
b11010 A
b11010 =
05
b100 S
b1001 2
b1001 ?
b1001 C
b1001 M
b11010 <
b11010 L
0;
b10 U
1#
#400000000000
0#
#405000000000
17
16
b10 S
1;
b100 U
0"
0P
0T
b100011 '
b100011 .
b100011 G
b10110 (
b10110 /
b10110 H
1#
#410000000000
0#
#415000000000
07
b10110 A
b10110 =
06
b100 S
b100011 2
b100011 ?
b100011 C
b100011 M
b10110 <
b10110 L
0;
b10 U
1#
#420000000000
0#
#425000000000
b10 S
17
16
1;
b100 U
1#
#430000000000
0#
#435000000000
07
06
b1 S
0*
0$
b10 U
0"
0P
0O
1%
1#
#440000000000
0#
#445000000000
b1 U
03
04
bx A
bx =
0T
bx <
bx L
0;
01
07
06
0"
0P
0O
1$
1#
#450000000000
0#
#455000000000
b10 S
1*
1#
#460000000000
0#
#465000000000
x3
x4
1"
1P
1T
1O
b100 S
b10 U
1#
#470000000000
0#
#475000000000
0T
b1 S
b100 U
1#
#480000000000
0#
#485000000000
03
04
0"
0P
0O
b10 S
b1 U
b0 ,
1#
#490000000000
b0 &
b0 -
b0 F
b0 )
0#
#495000000000
b0 A
b0 =
03
14
b100 S
b0 <
b0 L
b10 U
1#
#500000000000
b1 ,
0#
#505000000000
b0 :
b0 E
b10 S
17
b0 9
b0 >
b0 @
16
1;
b100 U
1#
#510000000000
b1 &
b1 -
b1 F
b1 )
0#
#515000000000
07
b1 A
b1 =
06
b100 S
b1 <
b1 L
0;
b10 U
1#
#520000000000
b10 ,
0#
#525000000000
b10 :
b10 E
b0 !
b0 0
b0 N
b10 S
17
b10 9
b10 >
b1 @
16
1;
b100 U
1#
#530000000000
b10 &
b10 -
b10 F
b10 )
0#
#535000000000
07
b10 A
b10 =
06
b100 S
b10 <
b10 L
0;
b10 U
1#
#540000000000
b11 ,
0#
#545000000000
b100 :
b100 E
b10 !
b10 0
b10 N
b10 S
17
b100 9
b100 >
b10 @
16
1;
b100 U
1#
#550000000000
b11 &
b11 -
b11 F
b11 )
0#
#555000000000
07
b11 A
b11 =
06
b100 S
b11 <
b11 L
0;
b10 U
1#
#560000000000
b100 ,
0#
#565000000000
b110 :
b110 E
b100 !
b100 0
b100 N
b10 S
17
b110 9
b110 >
b11 @
16
1;
b100 U
1#
#570000000000
b100 &
b100 -
b100 F
b100 )
0#
#575000000000
07
b100 A
b100 =
06
b100 S
b100 <
b100 L
0;
b10 U
1#
#580000000000
b101 ,
0#
#585000000000
b1000 :
b1000 E
b110 !
b110 0
b110 N
b10 S
17
b1000 9
b1000 >
b100 @
16
1;
b100 U
1#
#590000000000
b101 &
b101 -
b101 F
b101 )
0#
#595000000000
07
b101 A
b101 =
06
b100 S
b101 <
b101 L
0;
b10 U
1#
#600000000000
b110 ,
0#
#605000000000
b1010 :
b1010 E
b1000 !
b1000 0
b1000 N
b10 S
17
b1010 9
b1010 >
b101 @
16
1;
b100 U
1#
#610000000000
b110 &
b110 -
b110 F
b110 )
0#
#615000000000
07
b110 A
b110 =
06
b100 S
b110 <
b110 L
0;
b10 U
1#
#620000000000
b111 ,
0#
#625000000000
b1100 :
b1100 E
b1010 !
b1010 0
b1010 N
b10 S
17
b1100 9
b1100 >
b110 @
16
1;
b100 U
1#
#630000000000
b111 &
b111 -
b111 F
b111 )
0#
#635000000000
07
b111 A
b111 =
06
b100 S
b111 <
b111 L
0;
b10 U
1#
#640000000000
b1000 ,
0#
#645000000000
b1110 :
b1110 E
b1100 !
b1100 0
b1100 N
b10 S
17
b1110 9
b1110 >
b111 @
16
1;
b100 U
b0 ,
1#
#650000000000
b0 &
b0 -
b0 F
b0 )
0#
#655000000000
07
b0 A
b0 =
06
b100 S
b0 <
b0 L
0;
b10 U
1#
#660000000000
b1 ,
0#
#665000000000
b0 :
b0 E
b1110 !
b1110 0
b1110 N
b10 S
17
b0 9
b0 >
b0 @
16
1;
b100 U
1#
#670000000000
b1 &
b1 -
b1 F
b1 )
0#
#675000000000
07
b1 A
b1 =
06
b100 S
b1 <
b1 L
0;
b10 U
1#
#680000000000
b10 ,
0#
#685000000000
b10 :
b10 E
b0 !
b0 0
b0 N
b10 S
17
b10 9
b10 >
b1 @
16
1;
b100 U
1#
#690000000000
b10 &
b10 -
b10 F
b10 )
0#
#695000000000
07
b10 A
b10 =
06
b100 S
b10 <
b10 L
0;
b10 U
1#
#700000000000
b11 ,
0#
#705000000000
b100 :
b100 E
b10 !
b10 0
b10 N
b10 S
17
b100 9
b100 >
b10 @
16
1;
b100 U
1#
#710000000000
b11 &
b11 -
b11 F
b11 )
0#
#715000000000
07
b11 A
b11 =
06
b100 S
b11 <
b11 L
0;
b10 U
1#
#720000000000
b100 ,
0#
#725000000000
b110 :
b110 E
b100 !
b100 0
b100 N
b10 S
17
b110 9
b110 >
b11 @
16
1;
b100 U
1#
#730000000000
b100 &
b100 -
b100 F
b100 )
0#
#735000000000
07
b100 A
b100 =
06
b100 S
b100 <
b100 L
0;
b10 U
1#
#740000000000
b101 ,
0#
#745000000000
b1000 :
b1000 E
b110 !
b110 0
b110 N
b10 S
17
b1000 9
b1000 >
b100 @
16
1;
b100 U
1#
#750000000000
b101 &
b101 -
b101 F
b101 )
0#
#755000000000
07
b101 A
b101 =
06
b100 S
b101 <
b101 L
0;
b10 U
1#
#760000000000
b110 ,
0#
#765000000000
b1010 :
b1010 E
b1000 !
b1000 0
b1000 N
b10 S
17
b1010 9
b1010 >
b101 @
16
1;
b100 U
1#
#770000000000
b110 &
b110 -
b110 F
b110 )
0#
#775000000000
07
b110 A
b110 =
06
b100 S
b110 <
b110 L
0;
b10 U
1#
#780000000000
b111 ,
0#
#785000000000
b1100 :
b1100 E
b1010 !
b1010 0
b1010 N
b10 S
17
b1100 9
b1100 >
b110 @
16
1;
b100 U
1#
#790000000000
b111 &
b111 -
b111 F
b111 )
0#
#795000000000
07
b111 A
b111 =
06
b100 S
b111 <
b111 L
0;
b10 U
1#
#800000000000
b1000 ,
0#
#805000000000
b1110 :
b1110 E
b1100 !
b1100 0
b1100 N
b10 S
17
b1110 9
b1110 >
b111 @
16
1;
b100 U
1#
#810000000000
0#
#815000000000
07
06
b100 S
0;
b10 U
1#
#820000000000
0#
#825000000000
b1110 !
b1110 0
b1110 N
b10 S
17
16
1;
b100 U
b0 ,
1#
#830000000000
b100000000 &
b100000000 -
b100000000 F
b0 )
0#
